locationiq/__init__.py
locationiq/geocoder.py
locationiq/locationiq.py
locationiq-0.0.2.dist-info/METADATA
locationiq-0.0.2.dist-info/RECORD
locationiq-0.0.2.dist-info/WHEEL
locationiq-0.0.2.dist-info/top_level.txt
